pyaskalono-0.1.3.dist-info/METADATA
pyaskalono-0.1.3.dist-info/WHEEL
pyaskalono-0.1.3.dist-info/license_files/LICENSE
askalono/__init__.py
askalono/askalono.cpython-313-x86_64-linux-gnu.so
pyaskalono-0.1.3.dist-info/RECORD
