Metadata-Version: 2.1
Name: pyaskalono
Version: 0.1.3
License-File: LICENSE
Summary: Python bindings for askalono - rust library to detect license texts
Author: Sergei Silnov <po@kumekay.com>
Author-email: Sergei Silnov <po@kumekay.com>
Requires-Python: >=3.7
Project-URL: homepage, https://github.com/kumekay/pyaskalono
